MANIFEST.in
README
setup.cfg
setup.py
doc/changes.rst
doc/conf.py
doc/hacking.rst
doc/index.rst
doc/installation.rst
doc/reference.rst
doc/usage.rst
doc/reference/schema.rst
linaro_json/__init__.py
linaro_json/extensions.py
linaro_json/schema.py
linaro_json.egg-info/PKG-INFO
linaro_json.egg-info/SOURCES.txt
linaro_json.egg-info/dependency_links.txt
linaro_json.egg-info/requires.txt
linaro_json.egg-info/top_level.txt
linaro_json.egg-info/zip-safe
linaro_json/tests/__init__.py
linaro_json/tests/test_extensions.py
linaro_json/tests/test_schema.py