Metadata-Version: 1.0
Name: linaro-json
Version: 2.0.1
Summary: JSON Schema Validator
Home-page: https://launchpad.net/linaro-python-json
Author: Zygmunt Krynicki
Author-email: zygmunt.krynicki@linaro.org
License: UNKNOWN
Platform: UNKNOWN
Classifier: Development Status :: 4 - Beta
Classifier: Intended Audience :: Developers
Classifier: License :: OSI Approved :: GNU Library or Lesser General Public License (LGPL)
Classifier: Operating System :: OS Independent
Classifier: Programming Language :: Python :: 2.6
Classifier: Programming Language :: Python :: 2.7
